altair/__init__.py
altair/_magics.py
altair/datasets.py
altair/examples/__init__.py
altair/examples/airport_connections.py
altair/examples/airports.py
altair/examples/airports_count.py
altair/examples/anscombe_plot.py
altair/examples/area_chart_gradient.py
altair/examples/bar_and_line_with_dual_axis.py
altair/examples/bar_chart_horizontal.py
altair/examples/bar_chart_sorted.py
altair/examples/bar_chart_trellis_compact.py
altair/examples/bar_chart_with_highlighted_bar.py
altair/examples/bar_chart_with_highlighted_segment.py
altair/examples/bar_chart_with_labels.py
altair/examples/bar_chart_with_mean_line.py
altair/examples/bar_chart_with_negatives.py
altair/examples/bar_rounded.py
altair/examples/bar_with_rolling_mean.py
altair/examples/beckers_barley_trellis_plot.py
altair/examples/beckers_barley_wrapped_facet.py
altair/examples/binned_heatmap.py
altair/examples/binned_scatterplot.py
altair/examples/boxplot.py
altair/examples/bubble_plot.py
altair/examples/bump_chart.py
altair/examples/candlestick_chart.py
altair/examples/choropleth.py
altair/examples/choropleth_repeat.py
altair/examples/co2_concentration.py
altair/examples/comet_chart.py
altair/examples/connected_scatterplot.py
altair/examples/cumulative_count_chart.py
altair/examples/cumulative_wiki_donations.py
altair/examples/density_facet.py
altair/examples/density_stack.py
altair/examples/diverging_stacked_bar_chart.py
altair/examples/donut_chart.py
altair/examples/dot_dash_plot.py
altair/examples/errorbars_with_ci.py
altair/examples/errorbars_with_std.py
altair/examples/falkensee.py
altair/examples/filled_step_chart.py
altair/examples/gantt_chart.py
altair/examples/gapminder_bubble_plot.py
altair/examples/grouped_bar_chart.py
altair/examples/grouped_bar_chart_horizontal.py
altair/examples/grouped_bar_chart_with_error_bars.py
altair/examples/hexbins.py
altair/examples/histogram_responsive.py
altair/examples/histogram_with_a_global_mean_overlay.py
altair/examples/horizon_graph.py
altair-4.2.1.dist-info/LICENSE
altair-4.2.1.dist-info/METADATA
altair-4.2.1.dist-info/WHEEL
altair-4.2.1.dist-info/top_level.txt
altair-4.2.1.dist-info/RECORD
