Metadata-Version: 2.1
Name: altair
Version: 4.2.1
Summary: Altair: A declarative statistical visualization library for Python.
Home-page: http://altair-viz.github.io
Download-URL: http://github.com/altair-viz/altair/
Author: Brian E. Granger / Jake VanderPlas
Author-email: jakevdp@gmail.com
License: BSD 3-clause
Classifier: Development Status :: 5 - Production/Stable
Classifier: Environment :: Console
Classifier: Intended Audience :: Science/Research
Classifier: License :: OSI Approved :: BSD License
Classifier: Natural Language :: English
Classifier: Programming Language :: Python :: 3.7
Classifier: Programming Language :: Python :: 3.8
Classifier: Programming Language :: Python :: 3.9
Classifier: Programming Language :: Python :: 3.10
Requires-Python: >=3.7
Provides-Extra: dev
License-File: LICENSE
